tgim/common/blocks.py
tgim/common/model.py
tgim/models/fastvit.py
tgim/models/focalnet.py
tgim/models/ghostnetv2.py
tgim/models/repvit.py
tgim/models/shufflenetv2.py
tgim/models/shvit.py
tgim-0.0.0.dist-info/LICENSE
tgim-0.0.0.dist-info/METADATA
tgim-0.0.0.dist-info/WHEEL
tgim-0.0.0.dist-info/top_level.txt
tgim-0.0.0.dist-info/RECORD
