Metadata-Version: 2.1
Name: tgim
Version: 0.0.0
Summary: tinygrad Image Models
Author: wozeparrot
License: Apache-2.0
Requires-Python: >=3.10
License-File: LICENSE
Requires-Dist: tinygrad
